decorator_logging/__init__.py
decorator_logging/decorator.py
decorator_logging/log_level.py
decorator_logging/log_timing.py
decorator_logger-1.0.3.dist-info/METADATA
decorator_logger-1.0.3.dist-info/WHEEL
decorator_logger-1.0.3.dist-info/top_level.txt
decorator_logger-1.0.3.dist-info/RECORD
