Metadata-Version: 2.4
Name: decorator_logger
Version: 1.0.3
Summary: Simple decorator-logger
Home-page: https://github.com/ArgentumX/decorator-logger-library
Author: argentumx
Author-email: example@gmail.com
Project-URL: GitHub, https://github.com/ArgentumX/
Keywords: aop logger decorator
Classifier: Programming Language :: Python :: 3.11
Classifier: License :: OSI Approved :: MIT License
Requires-Python: >=3.6
Requires-Dist: loguru>=0.7.3
Dynamic: author
Dynamic: author-email
Dynamic: classifier
Dynamic: description
Dynamic: description-content-type
Dynamic: home-page
Dynamic: keywords
Dynamic: project-url
Dynamic: requires-dist
Dynamic: requires-python
Dynamic: summary
